hhdpy/__init__.py
hhdpy/__main__.py
hhdpy/and_clone_2_install.py
hhdpy/jupyter.py
hhdpy/my_util.py
hhdpy/tex.py
hhdpy/typora.py
hhdpy-1.0.8.dist-info/LICENSE
hhdpy-1.0.8.dist-info/METADATA
hhdpy-1.0.8.dist-info/WHEEL
hhdpy-1.0.8.dist-info/entry_points.txt
hhdpy-1.0.8.dist-info/top_level.txt
hhdpy-1.0.8.dist-info/RECORD
