Metadata-Version: 2.1
Name: hhdpy
Version: 1.0.8
Summary: hhd2002를 위한 파이썬 커맨드라인 유틸리티
Home-page: https://github.com/HyundongHwang/hhdpy
Author: hhd2002
Author-email: h2d2002@naver.com
License: UNKNOWN
Keywords: hhdpy,hhd2002,utility
Platform: UNKNOWN
Requires-Python: >=3
License-File: LICENSE
